hw/memory.sv

module memory(
	#(parameter
	WORD_SIZE = 16,					// Size of RAM words
	NUM_WORDS = 16,            			// Number of words to store in RAM
	ADDR_BITS = 4)         				// Number of RAM address bits
	(input logic   		      	clk,    	// Clock
	 input logic 			we,		// Write enable
	 input logic [ADDR_BITS-1:0]	addr,		// Address to read/write
	 input logic [WORD_SIZE-1:0] 	data_in,	// Data to write
	 output logic [WORD_SIZE-1:0] 	data_out);	// Data to read


	 logic [WORD_SIZE-1:0] 	mem[NUM_WORDS - 1:0];

	 always_ff @(posedge clk) begin
		 if (we) mem[addr] <= data_in;
		 data_out <= mem[addr];
	 end

endmodule

hw/tb/memory.vcd
$version Generated by VerilatedVcd $end
$date Fri Apr 29 09:57:59 2022
 $end
$timescale   1ns $end

 $scope module TOP $end
  $var wire  4 U! addr [3:0] $end
  $var wire  1 E! clk $end
  $var wire 32 ]! data_in [31:0] $end
  $var wire 32 e! data_out [31:0] $end
  $var wire  1 M! we $end
  $scope module memory $end
   $var wire 32 }! ADDR_BITS [31:0] $end
   $var wire 32 u! NUM_WORDS [31:0] $end
   $var wire 32 m! WORD_SIZE [31:0] $end
   $var wire  4 U! addr [3:0] $end
   $var wire  1 E! clk $end
   $var wire 32 ]! data_in [31:0] $end
   $var wire 32 e! data_out [31:0] $end
   $var wire 32 # mem(0) [31:0] $end
   $var wire 32 $ mem(1) [31:0] $end
   $var wire 32 - mem(10) [31:0] $end
   $var wire 32 . mem(11) [31:0] $end
   $var wire 32 / mem(12) [31:0] $end
   $var wire 32 0 mem(13) [31:0] $end
   $var wire 32 1 mem(14) [31:0] $end
   $var wire 32 2 mem(15) [31:0] $end
   $var wire 32 % mem(2) [31:0] $end
   $var wire 32 & mem(3) [31:0] $end
   $var wire 32 ' mem(4) [31:0] $end
   $var wire 32 ( mem(5) [31:0] $end
   $var wire 32 ) mem(6) [31:0] $end
   $var wire 32 * mem(7) [31:0] $end
   $var wire 32 + mem(8) [31:0] $end
   $var wire 32 , mem(9) [31:0] $end
   $var wire  1 M! we $end
  $upscope $end
 $upscope $end
$enddefinitions $end


#10
b00000000000000000000000000000000 #
b00000000000000000000000000000000 $
b00000000000000000000000000000000 %
b00000000000000000000000000000000 &
b00000000000000000000000000000000 '
b00000000000000000000000000000000 (
b00000000000000000000000000000000 )
b00000000000000000000000000000000 *
b00000000000000000000000000000000 +
b00000000000000000000000000000000 ,
b00000000000000000000000000000000 -
b00000000000000000000000000000000 .
b00000000000000000000000000000000 /
b00000000000000000000000000000000 0
b00000000000000000000000000000000 1
b00000000000000000000000000000000 2
0E!
1M!
b0000 U!
b00000000000000000000000000000000 ]!
b00000000000000000000000000000000 e!
b00000000000000000000000000100000 m!
b00000000000000000000000000010000 u!
b00000000000000000000000000000100 }!
#20
1E!
#30
0E!
b0001 U!
b00000000000000000000000000000001 ]!
#40
b00000000000000000000000000000001 $
1E!
#50
0E!
b0010 U!
b00000000000000000000000000000010 ]!
#60
b00000000000000000000000000000010 %
1E!
#70
0E!
b0011 U!
b00000000000000000000000000000011 ]!
#80
b00000000000000000000000000000011 &
1E!
#90
0E!
b0100 U!
b00000000000000000000000000000100 ]!
#100
b00000000000000000000000000000100 '
1E!
#110
0E!
b0101 U!
b00000000000000000000000000000101 ]!
#120
b00000000000000000000000000000101 (
1E!
#130
0E!
b0110 U!
b00000000000000000000000000000110 ]!
#140
b00000000000000000000000000000110 )
1E!
#150
0E!
b0111 U!
b00000000000000000000000000000111 ]!
#160
b00000000000000000000000000000111 *
1E!
#170
0E!
b1000 U!
b00000000000000000000000000001000 ]!
#180
b00000000000000000000000000001000 +
1E!
#190
0E!
b1001 U!
b00000000000000000000000000001001 ]!
#200
b00000000000000000000000000001001 ,
1E!
#210
0E!
b1010 U!
b00000000000000000000000000001010 ]!
#220
b00000000000000000000000000001010 -
1E!
#230
0E!
b1011 U!
b00000000000000000000000000001011 ]!
#240
b00000000000000000000000000001011 .
1E!
#250
0E!
b1100 U!
b00000000000000000000000000001100 ]!
#260
b00000000000000000000000000001100 /
1E!
#270
0E!
b1101 U!
b00000000000000000000000000001101 ]!
#280
b00000000000000000000000000001101 0
1E!
#290
0E!
b1110 U!
b00000000000000000000000000001110 ]!
#300
b00000000000000000000000000001110 1
1E!
#310
0E!
b1111 U!
b00000000000000000000000000001111 ]!
#320
b00000000000000000000000000001111 2
1E!
#330
0E!
0M!
b0000 U!
#340
1E!
#350
0E!
b0001 U!
#360
1E!
b00000000000000000000000000000001 e!
#370
0E!
b0010 U!
#380
1E!
b00000000000000000000000000000010 e!
#390
0E!
b0011 U!
#400
1E!
b00000000000000000000000000000011 e!
#410
0E!
b0100 U!
#420
1E!
b00000000000000000000000000000100 e!
#430
0E!
b0101 U!
#440
1E!
b00000000000000000000000000000101 e!
#450
0E!
b0110 U!
#460
1E!
b00000000000000000000000000000110 e!
#470
0E!
b0111 U!
#480
1E!
b00000000000000000000000000000111 e!
#490
0E!
b1000 U!
#500
1E!
b00000000000000000000000000001000 e!
#510
0E!
b1001 U!
#520
1E!
b00000000000000000000000000001001 e!
#530
0E!
b1010 U!
#540
1E!
b00000000000000000000000000001010 e!
#550
0E!
b1011 U!
#560
1E!
b00000000000000000000000000001011 e!
#570
0E!
b1100 U!
#580
1E!
b00000000000000000000000000001100 e!
#590
0E!
b1101 U!
#600
1E!
b00000000000000000000000000001101 e!
#610
0E!
b1110 U!
#620
1E!
b00000000000000000000000000001110 e!
#630
0E!
b1111 U!
#640
1E!
b00000000000000000000000000001111 e!
