hw/src/shift.sv

module shift
	(input logic 		 clk,
	 input logic 		 en,
	 input logic 		 ld,
	 input logic [47:0] 	 data_in,
	 output logic [2:0]  	 data_out);

	 logic [2:0] mem[15:0];
	 
	always_ff @(posedge clk) begin
		if (en) begin
			mem[0] 	<= 3'b0;
			mem[1] 	<= mem[0];
			mem[2] 	<= mem[1];
			mem[3] 	<= mem[2];
			mem[4] 	<= mem[3];
			mem[5] 	<= mem[4];
			mem[6] 	<= mem[5];
			mem[7] 	<= mem[6];
			mem[8] 	<= mem[7];
			mem[9] 	<= mem[8];
			mem[10] <= mem[9];
			mem[11] <= mem[10];
			mem[12] <= mem[11];
			mem[13] <= mem[12];
			mem[14] <= mem[13];
			mem[15] <= mem[14];
			data_out <= mem[15];
		end
		if (ld) begin
			mem[0] 	<= data_in[47:45];
			mem[1] 	<= data_in[44:42]; 
			mem[2] 	<= data_in[41:39]; 
			mem[3] 	<= data_in[38:36]; 
			mem[4] 	<= data_in[35:33]; 
			mem[5] 	<= data_in[32:30]; 
			mem[6] 	<= data_in[29:27]; 
			mem[7] 	<= data_in[26:24]; 
			mem[8] 	<= data_in[23:21]; 
			mem[9] 	<= data_in[20:18]; 
			mem[10] <= data_in[17:15]; 
			mem[11] <= data_in[14:12]; 
			mem[12] <= data_in[11:9]; 
			mem[13] <= data_in[8:6]; 
			mem[14] <= data_in[5:3]; 
			mem[15] <= data_in[2:0]; 
		//	mem[0] 	<= data_in[63:60];
		//	mem[1] 	<= data_in[59:56]; 
		//	mem[2] 	<= data_in[55:52]; 
		//	mem[3] 	<= data_in[51:48]; 
		//	mem[4] 	<= data_in[47:44]; 
		//	mem[5] 	<= data_in[43:40]; 
		//	mem[6] 	<= data_in[39:36]; 
		//	mem[7] 	<= data_in[35:32]; 
		//	mem[8] 	<= data_in[31:28]; 
		//	mem[9] 	<= data_in[27:24]; 
		//	mem[10] <= data_in[23:20]; 
		//	mem[11] <= data_in[19:16]; 
		//	mem[12] <= data_in[15:12]; 
		//	mem[13] <= data_in[11:8]; 
		//	mem[14] <= data_in[7:3]; 
		//	mem[15] <= data_in[2:0]; 
		end
	end
	//assign data_out = mem[15];
 endmodule

hw/tb/shift.vcd
$version Generated by VerilatedVcd $end
$date Fri Apr 22 13:58:59 2022
 $end
$timescale   1ns $end

 $scope module TOP $end
  $var wire  1 E! clk $end
  $var wire 48 ]! data_in [47:0] $end
  $var wire  3 m! data_out [2:0] $end
  $var wire  1 M! en $end
  $var wire  1 U! ld $end
  $scope module shift $end
   $var wire  1 E! clk $end
   $var wire 48 ]! data_in [47:0] $end
   $var wire  3 m! data_out [2:0] $end
   $var wire  1 M! en $end
   $var wire  1 U! ld $end
   $var wire  3 # mem(0) [2:0] $end
   $var wire  3 $ mem(1) [2:0] $end
   $var wire  3 - mem(10) [2:0] $end
   $var wire  3 . mem(11) [2:0] $end
   $var wire  3 / mem(12) [2:0] $end
   $var wire  3 0 mem(13) [2:0] $end
   $var wire  3 1 mem(14) [2:0] $end
   $var wire  3 2 mem(15) [2:0] $end
   $var wire  3 % mem(2) [2:0] $end
   $var wire  3 & mem(3) [2:0] $end
   $var wire  3 ' mem(4) [2:0] $end
   $var wire  3 ( mem(5) [2:0] $end
   $var wire  3 ) mem(6) [2:0] $end
   $var wire  3 * mem(7) [2:0] $end
   $var wire  3 + mem(8) [2:0] $end
   $var wire  3 , mem(9) [2:0] $end
  $upscope $end
 $upscope $end
$enddefinitions $end


#10
b000 #
b000 $
b000 %
b000 &
b000 '
b000 (
b000 )
b000 *
b000 +
b000 ,
b000 -
b000 .
b000 /
b000 0
b000 1
b000 2
0E!
0M!
1U!
b000001010011100101110111000001010011100101110111 ]!
b000 m!
#20
b001 $
b010 %
b011 &
b100 '
b101 (
b110 )
b111 *
b001 ,
b010 -
b011 .
b100 /
b101 0
b110 1
b111 2
1E!
#30
0E!
#40
1E!
#50
0E!
#60
1E!
#70
0E!
#80
1E!
#90
0E!
#100
1E!
#110
0E!
#120
1E!
#130
0E!
#140
1E!
#150
0E!
#160
1E!
#170
0E!
#180
1E!
#190
0E!
#200
1E!
#210
0E!
#220
1E!
#230
0E!
#240
1E!
#250
0E!
#260
1E!
#270
0E!
#280
1E!
#290
0E!
#300
1E!
#310
0E!
#320
1E!
#330
0E!
1M!
0U!
#340
b000 $
b001 %
b010 &
b011 '
b100 (
b101 )
b110 *
b111 +
b000 ,
b001 -
b010 .
b011 /
b100 0
b101 1
b110 2
1E!
b111 m!
#350
0E!
#360
b000 %
b001 &
b010 '
b011 (
b100 )
b101 *
b110 +
b111 ,
b000 -
b001 .
b010 /
b011 0
b100 1
b101 2
1E!
b110 m!
#370
0E!
#380
b000 &
b001 '
b010 (
b011 )
b100 *
b101 +
b110 ,
b111 -
b000 .
b001 /
b010 0
b011 1
b100 2
1E!
b101 m!
#390
0E!
#400
b000 '
b001 (
b010 )
b011 *
b100 +
b101 ,
b110 -
b111 .
b000 /
b001 0
b010 1
b011 2
1E!
b100 m!
#410
0E!
#420
b000 (
b001 )
b010 *
b011 +
b100 ,
b101 -
b110 .
b111 /
b000 0
b001 1
b010 2
1E!
b011 m!
#430
0E!
#440
b000 )
b001 *
b010 +
b011 ,
b100 -
b101 .
b110 /
b111 0
b000 1
b001 2
1E!
b010 m!
#450
0E!
#460
b000 *
b001 +
b010 ,
b011 -
b100 .
b101 /
b110 0
b111 1
b000 2
1E!
b001 m!
#470
0E!
#480
b000 +
b001 ,
b010 -
b011 .
b100 /
b101 0
b110 1
b111 2
1E!
b000 m!
#490
0E!
#500
b000 ,
b001 -
b010 .
b011 /
b100 0
b101 1
b110 2
1E!
b111 m!
#510
0E!
#520
b000 -
b001 .
b010 /
b011 0
b100 1
b101 2
1E!
b110 m!
#530
0E!
#540
b000 .
b001 /
b010 0
b011 1
b100 2
1E!
b101 m!
#550
0E!
#560
b000 /
b001 0
b010 1
b011 2
1E!
b100 m!
#570
0E!
#580
b000 0
b001 1
b010 2
1E!
b011 m!
#590
0E!
#600
b000 1
b001 2
1E!
b010 m!
#610
0E!
#620
b000 2
1E!
b001 m!
#630
0E!
#640
1E!
b000 m!
