hw/src/shift.sv

module shift
	(input logic 		      clk,
	 input logic 		      en,
	 input logic 		      ld,
	 input logic [47:0] 	      data_in,
	 output logic [2:0] data_out);

	 logic [2:0] mem[15:0];
	 
	always_ff @(posedge clk) begin
		if (en) begin
			mem[0] 	<= 3'b0;
			mem[1] 	<= mem[0];
			mem[2] 	<= mem[1];
			mem[3] 	<= mem[2];
			mem[4] 	<= mem[3];
			mem[5] 	<= mem[4];
			mem[6] 	<= mem[5];
			mem[7] 	<= mem[6];
			mem[8] 	<= mem[7];
			mem[9] 	<= mem[8];
			mem[10] <= mem[9];
			mem[11] <= mem[10];
			mem[12] <= mem[11];
			mem[13] <= mem[12];
			mem[14] <= mem[13];
			mem[15] <= mem[14];
			data_out <= mem[15];
		end
		if (ld) begin
			mem[0] 	<= data_in[47:45];
			mem[1] 	<= data_in[44:42]; 
			mem[2] 	<= data_in[41:39]; 
			mem[3] 	<= data_in[38:36]; 
			mem[4] 	<= data_in[35:33]; 
			mem[5] 	<= data_in[32:30]; 
			mem[6] 	<= data_in[29:27]; 
			mem[7] 	<= data_in[26:24]; 
			mem[8] 	<= data_in[23:21]; 
			mem[9] 	<= data_in[20:18]; 
			mem[10] <= data_in[17:15]; 
			mem[11] <= data_in[14:12]; 
			mem[12] <= data_in[11:9]; 
			mem[13] <= data_in[8:6]; 
			mem[14] <= data_in[5:3]; 
			mem[15] <= data_in[2:0]; 
		//	mem[0] 	<= data_in[63:60];
		//	mem[1] 	<= data_in[59:56]; 
		//	mem[2] 	<= data_in[55:52]; 
		//	mem[3] 	<= data_in[51:48]; 
		//	mem[4] 	<= data_in[47:44]; 
		//	mem[5] 	<= data_in[43:40]; 
		//	mem[6] 	<= data_in[39:36]; 
		//	mem[7] 	<= data_in[35:32]; 
		//	mem[8] 	<= data_in[31:28]; 
		//	mem[9] 	<= data_in[27:24]; 
		//	mem[10] <= data_in[23:20]; 
		//	mem[11] <= data_in[19:16]; 
		//	mem[12] <= data_in[15:12]; 
		//	mem[13] <= data_in[11:8]; 
		//	mem[14] <= data_in[7:3]; 
		//	mem[15] <= data_in[2:0]; 
		end
	end
	//assign data_out = mem[15];
 endmodule

hw/tb/shift.vcd
$version Generated by VerilatedVcd $end
$date Sun Apr 10 01:35:20 2022 $end
$timescale 1ps $end

 $scope module TOP $end
  $var wire  1 3 clk $end
  $var wire 48 6 data_in [47:0] $end
  $var wire  3 8 data_out [2:0] $end
  $var wire  1 4 en $end
  $var wire  1 5 ld $end
  $scope module shift $end
   $var wire  1 3 clk $end
   $var wire 48 6 data_in [47:0] $end
   $var wire  3 8 data_out [2:0] $end
   $var wire  1 4 en $end
   $var wire  1 5 ld $end
   $var wire  3 # mem[0] [2:0] $end
   $var wire  3 - mem[10] [2:0] $end
   $var wire  3 . mem[11] [2:0] $end
   $var wire  3 / mem[12] [2:0] $end
   $var wire  3 0 mem[13] [2:0] $end
   $var wire  3 1 mem[14] [2:0] $end
   $var wire  3 2 mem[15] [2:0] $end
   $var wire  3 $ mem[1] [2:0] $end
   $var wire  3 % mem[2] [2:0] $end
   $var wire  3 & mem[3] [2:0] $end
   $var wire  3 ' mem[4] [2:0] $end
   $var wire  3 ( mem[5] [2:0] $end
   $var wire  3 ) mem[6] [2:0] $end
   $var wire  3 * mem[7] [2:0] $end
   $var wire  3 + mem[8] [2:0] $end
   $var wire  3 , mem[9] [2:0] $end
  $upscope $end
 $upscope $end
$enddefinitions $end


#10
b000 #
b000 $
b000 %
b000 &
b000 '
b000 (
b000 )
b000 *
b000 +
b000 ,
b000 -
b000 .
b000 /
b000 0
b000 1
b000 2
03
04
15
b000001010011100101110111000001010011100101110111 6
b000 8
#20
b001 $
b010 %
b011 &
b100 '
b101 (
b110 )
b111 *
b001 ,
b010 -
b011 .
b100 /
b101 0
b110 1
b111 2
13
#30
03
#40
13
#50
03
#60
13
#70
03
#80
13
#90
03
#100
13
#110
03
#120
13
#130
03
#140
13
#150
03
#160
13
#170
03
#180
13
#190
03
#200
13
#210
03
#220
13
#230
03
#240
13
#250
03
#260
13
#270
03
#280
13
#290
03
#300
13
#310
03
#320
13
#330
03
14
05
#340
b000 $
b001 %
b010 &
b011 '
b100 (
b101 )
b110 *
b111 +
b000 ,
b001 -
b010 .
b011 /
b100 0
b101 1
b110 2
13
b111 8
#350
03
#360
b000 %
b001 &
b010 '
b011 (
b100 )
b101 *
b110 +
b111 ,
b000 -
b001 .
b010 /
b011 0
b100 1
b101 2
13
b110 8
#370
03
#380
b000 &
b001 '
b010 (
b011 )
b100 *
b101 +
b110 ,
b111 -
b000 .
b001 /
b010 0
b011 1
b100 2
13
b101 8
#390
03
#400
b000 '
b001 (
b010 )
b011 *
b100 +
b101 ,
b110 -
b111 .
b000 /
b001 0
b010 1
b011 2
13
b100 8
#410
03
#420
b000 (
b001 )
b010 *
b011 +
b100 ,
b101 -
b110 .
b111 /
b000 0
b001 1
b010 2
13
b011 8
#430
03
#440
b000 )
b001 *
b010 +
b011 ,
b100 -
b101 .
b110 /
b111 0
b000 1
b001 2
13
b010 8
#450
03
#460
b000 *
b001 +
b010 ,
b011 -
b100 .
b101 /
b110 0
b111 1
b000 2
13
b001 8
#470
03
#480
b000 +
b001 ,
b010 -
b011 .
b100 /
b101 0
b110 1
b111 2
13
b000 8
#490
03
#500
b000 ,
b001 -
b010 .
b011 /
b100 0
b101 1
b110 2
13
b111 8
#510
03
#520
b000 -
b001 .
b010 /
b011 0
b100 1
b101 2
13
b110 8
#530
03
#540
b000 .
b001 /
b010 0
b011 1
b100 2
13
b101 8
#550
03
#560
b000 /
b001 0
b010 1
b011 2
13
b100 8
#570
03
#580
b000 0
b001 1
b010 2
13
b011 8
#590
03
#600
b000 1
b001 2
13
b010 8
#610
03
#620
b000 2
13
b001 8
#630
03
#640
13
b000 8
