hw/src/shift.sv
// Reads an entire sprite into memory. Outputs 2 bits of that sprite per clock
// cycle. Shifts all remaining bits over one memory location.
module shift
	(input logic 		 clk,
	 input logic 		 en,
	 input logic 		 ld,
	 input logic [31:0] 	 data_in,
	 output logic [1:0]  	 data_out);

 	 // 16 memory locations each 2 bits in size.
	 logic [1:0] mem[15:0];
	 
	always_ff @(posedge clk) begin
		if (en) begin
			mem[0] 	<= 2'b0;
			mem[1] 	<= mem[0];
			mem[2] 	<= mem[1];
			mem[3] 	<= mem[2];
			mem[4] 	<= mem[3];
			mem[5] 	<= mem[4];
			mem[6] 	<= mem[5];
			mem[7] 	<= mem[6];
			mem[8] 	<= mem[7];
			mem[9] 	<= mem[8];
			mem[10] <= mem[9];
			mem[11] <= mem[10];
			mem[12] <= mem[11];
			mem[13] <= mem[12];
			mem[14] <= mem[13];
			mem[15] <= mem[14];
			data_out <= mem[15];
		end
		if (ld) begin
			mem[0] 	<= data_in[31:30];
			mem[1] 	<= data_in[29:28]; 
			mem[2] 	<= data_in[27:26]; 
			mem[3] 	<= data_in[25:24]; 
			mem[4] 	<= data_in[23:22]; 
			mem[5] 	<= data_in[21:20]; 
			mem[6] 	<= data_in[19:18]; 
			mem[7] 	<= data_in[17:16]; 
			mem[8] 	<= data_in[15:14]; 
			mem[9] 	<= data_in[13:12]; 
			mem[10] <= data_in[11:10]; 
			mem[11] <= data_in[9:8]; 
			mem[12] <= data_in[7:6]; 
			mem[13] <= data_in[5:4]; 
			mem[14] <= data_in[3:2]; 
			mem[15] <= data_in[1:0]; 
		end
	end
	//assign data_out = mem[15];
 endmodule

hw/tb/shift.vcd
$version Generated by VerilatedVcd $end
$date Fri Apr 29 10:19:35 2022
 $end
$timescale   1ns $end

 $scope module TOP $end
  $var wire  1 E! clk $end
  $var wire 32 ]! data_in [31:0] $end
  $var wire  2 e! data_out [1:0] $end
  $var wire  1 M! en $end
  $var wire  1 U! ld $end
  $scope module shift $end
   $var wire  1 E! clk $end
   $var wire 32 ]! data_in [31:0] $end
   $var wire  2 e! data_out [1:0] $end
   $var wire  1 M! en $end
   $var wire  1 U! ld $end
   $var wire  2 # mem(0) [1:0] $end
   $var wire  2 $ mem(1) [1:0] $end
   $var wire  2 - mem(10) [1:0] $end
   $var wire  2 . mem(11) [1:0] $end
   $var wire  2 / mem(12) [1:0] $end
   $var wire  2 0 mem(13) [1:0] $end
   $var wire  2 1 mem(14) [1:0] $end
   $var wire  2 2 mem(15) [1:0] $end
   $var wire  2 % mem(2) [1:0] $end
   $var wire  2 & mem(3) [1:0] $end
   $var wire  2 ' mem(4) [1:0] $end
   $var wire  2 ( mem(5) [1:0] $end
   $var wire  2 ) mem(6) [1:0] $end
   $var wire  2 * mem(7) [1:0] $end
   $var wire  2 + mem(8) [1:0] $end
   $var wire  2 , mem(9) [1:0] $end
  $upscope $end
 $upscope $end
$enddefinitions $end


#10
b00 #
b00 $
b00 %
b00 &
b00 '
b00 (
b00 )
b00 *
b00 +
b00 ,
b00 -
b00 .
b00 /
b00 0
b00 1
b00 2
0E!
0M!
1U!
b01110111000001010011100101110111 ]!
b00 e!
#20
b01 #
b11 $
b01 %
b11 &
b01 )
b01 *
b11 ,
b10 -
b01 .
b01 /
b11 0
b01 1
b11 2
1E!
#30
0E!
#40
1E!
#50
0E!
#60
1E!
#70
0E!
#80
1E!
#90
0E!
#100
1E!
#110
0E!
#120
1E!
#130
0E!
#140
1E!
#150
0E!
#160
1E!
#170
0E!
#180
1E!
#190
0E!
#200
1E!
#210
0E!
#220
1E!
#230
0E!
#240
1E!
#250
0E!
#260
1E!
#270
0E!
#280
1E!
#290
0E!
#300
1E!
#310
0E!
#320
1E!
#330
0E!
1M!
0U!
#340
b00 #
b01 $
b11 %
b01 &
b11 '
b00 )
b01 +
b00 ,
b11 -
b10 .
b01 0
b11 1
b01 2
1E!
b11 e!
#350
0E!
#360
b00 $
b01 %
b11 &
b01 '
b11 (
b00 *
b01 ,
b00 -
b11 .
b10 /
b01 1
b11 2
1E!
b01 e!
#370
0E!
#380
b00 %
b01 &
b11 '
b01 (
b11 )
b00 +
b01 -
b00 .
b11 /
b10 0
b01 2
1E!
b11 e!
#390
0E!
#400
b00 &
b01 '
b11 (
b01 )
b11 *
b00 ,
b01 .
b00 /
b11 0
b10 1
1E!
b01 e!
#410
0E!
#420
b00 '
b01 (
b11 )
b01 *
b11 +
b00 -
b01 /
b00 0
b11 1
b10 2
1E!
#430
0E!
#440
b00 (
b01 )
b11 *
b01 +
b11 ,
b00 .
b01 0
b00 1
b11 2
1E!
b10 e!
#450
0E!
#460
b00 )
b01 *
b11 +
b01 ,
b11 -
b00 /
b01 1
b00 2
1E!
b11 e!
#470
0E!
#480
b00 *
b01 +
b11 ,
b01 -
b11 .
b00 0
b01 2
1E!
b00 e!
#490
0E!
#500
b00 +
b01 ,
b11 -
b01 .
b11 /
b00 1
1E!
b01 e!
#510
0E!
#520
b00 ,
b01 -
b11 .
b01 /
b11 0
b00 2
1E!
#530
0E!
#540
b00 -
b01 .
b11 /
b01 0
b11 1
1E!
b00 e!
#550
0E!
#560
b00 .
b01 /
b11 0
b01 1
b11 2
1E!
#570
0E!
#580
b00 /
b01 0
b11 1
b01 2
1E!
b11 e!
#590
0E!
#600
b00 0
b01 1
b11 2
1E!
b01 e!
#610
0E!
#620
b00 1
b01 2
1E!
b11 e!
#630
0E!
#640
b00 2
1E!
b01 e!
